variational_autoencoder_pytorch/__init__.py
variational_autoencoder_pytorch/module.py
variational_autoencoder_pytorch-0.1.0.dist-info/licenses/LICENSE
variational_autoencoder_pytorch-0.1.0.dist-info/METADATA
variational_autoencoder_pytorch-0.1.0.dist-info/WHEEL
variational_autoencoder_pytorch-0.1.0.dist-info/top_level.txt
variational_autoencoder_pytorch-0.1.0.dist-info/RECORD
